ngtt/__init__.py
ngtt/exceptions.py
ngtt/orders.py
ngtt/protocol.py
ngtt/uplink/__init__.py
ngtt/uplink/connection.py
ngtt/uplink/thread.py
smok/__init__.py
smok/baob.py
smok/basics.py
smok/exceptions.py
smok/logging.py
smok/metadata.py
smok/certs/dev.crt
smok/certs/rapid.crt
smok/certs/root.crt
smok/client/__init__.py
smok/client/api.py
smok/client/certificate.py
smok/client/client.py
smok/client/slave.py
smok/extras/__init__.py
smok/extras/arch_database/__init__.py
smok/extras/arch_database/base.py
smok/extras/arch_database/in_memory.py
smok/extras/arch_database/pickling.py
smok/extras/baob_database/__init__.py
smok/extras/baob_database/base.py
smok/extras/baob_database/memory.py
smok/extras/baob_database/pickling.py
smok/extras/event_database/__init__.py
smok/extras/event_database/base.py
smok/extras/event_database/in_memory.py
smok/extras/event_database/null.py
smok/extras/event_database/pickling.py
smok/extras/macros_database/__init__.py
smok/extras/macros_database/base.py
smok/extras/macros_database/in_memory.py
smok/extras/macros_database/pickling.py
smok/extras/metadata_database/__init__.py
smok/extras/metadata_database/base.py
smok/extras/metadata_database/in_memory.py
smok/extras/metadata_database/pickling.py
smok/extras/pp_database/__init__.py
smok/extras/pp_database/base.py
smok/extras/pp_database/in_memory.py
smok/extras/pp_database/pickling.py
smok/extras/pred_database/__init__.py
smok/extras/pred_database/base.py
smok/extras/pred_database/in_memory.py
smok/extras/pred_database/pickling.py
smok/extras/sensor_write_database/__init__.py
smok/extras/sensor_write_database/base.py
smok/extras/sensor_write_database/in_memory.py
smok/extras/sensor_write_database/pickling.py
smok/extras/sensors_database/__init__.py
smok/extras/sensors_database/base.py
smok/extras/sensors_database/in_memory.py
smok/extras/sensors_database/pickling.py
smok/macro/__init__.py
smok/macro/macro.py
smok/pathpoint/__init__.py
smok/pathpoint/orders.py
smok/pathpoint/pathpoint.py
smok-0.21.0.dist-info/LICENSE
smok-0.21.0.dist-info/METADATA
smok-0.21.0.dist-info/WHEEL
smok-0.21.0.dist-info/top_level.txt
smok-0.21.0.dist-info/RECORD
