Metadata-Version: 2.1
Name: smok
Version: 0.21.0
Summary: Library for writing services that behave as SMOK devices
Home-page: https://github.com/smok-serwis/smok-client
Author: Piotr Maślanka
Author-email: pmaslanka@smok.co
License: UNKNOWN
Project-URL: Documentation, https://smok-client.readthedocs.io/
Project-URL: Code, https://github.com/smok-serwis/smok-client
Project-URL: Issue tracker, https://github.com/smok-serwis/smok-client/issues
Keywords: iot,client,smok,upload,scada
Platform: UNKNOWN
Classifier: Programming Language :: Python
Classifier: Programming Language :: Python :: 3.6
Classifier: Programming Language :: Python :: 3.7
Classifier: Programming Language :: Python :: 3.8
Classifier: Programming Language :: Python :: 3.9
Classifier: Programming Language :: Python :: Implementation :: CPython
Classifier: Programming Language :: Python :: Implementation :: PyPy
Classifier: Operating System :: POSIX
Classifier: Operating System :: OS Independent
Classifier: Development Status :: 4 - Beta
Classifier: License :: OSI Approved :: MIT License
Classifier: Topic :: Software Development :: Libraries
Requires-Python: !=2.7.*,!=3.0.*,!=3.1.*,!=3.2.*,!=3.3.*,!=3.4.*,!=3.5.*
Requires-Dist: satella (>=2.17.19)
Requires-Dist: requests
Requires-Dist: pyasn1
Requires-Dist: cryptography
Requires-Dist: pyopenssl
Requires-Dist: pytz
Requires-Dist: ujson
Requires-Dist: minijson
